omegatomo/cpp/ArrayFire_OpenCL_device_info.cpp
omegatomo/cpp/GATE_root_matlab.cpp
omegatomo/cpp/GATE_root_matlab_C.cpp
omegatomo/cpp/GATE_root_matlab_oct.cpp
omegatomo/cpp/GATE_root_matlab_uint16.cpp
omegatomo/cpp/GGMRF.h
omegatomo/cpp/MRP.h
omegatomo/cpp/NLM.h
omegatomo/cpp/NLM_func.cpp
omegatomo/cpp/NLM_funcSingle.cpp
omegatomo/cpp/OpenCL_device_info.cpp
omegatomo/cpp/OpenCL_matrixfree.cpp
omegatomo/cpp/OpenCL_matrixfree_multi_gpu.cpp
omegatomo/cpp/ProjectorClass.h
omegatomo/cpp/ProjectorClassCPU.h
omegatomo/cpp/ProjectorClassCUDA.h
omegatomo/cpp/RDP.h
omegatomo/cpp/TV.h
omegatomo/cpp/algorithms.h
omegatomo/cpp/computeForwardProject.h
omegatomo/cpp/createSinogram.cpp
omegatomo/cpp/createSinogramASCII.cpp
omegatomo/cpp/createSinogramASCIICPP.cpp
omegatomo/cpp/createSinogramASCIIOct.cpp
omegatomo/cpp/cuda_error.h
omegatomo/cpp/dIndices.h
omegatomo/cpp/functions.hpp
omegatomo/cpp/functions_multigpu.hpp
omegatomo/cpp/gate_lmf_matlab.cpp
omegatomo/cpp/hyperbolicPrior.h
omegatomo/cpp/improved_Siddon_algorithm_discard.cpp
omegatomo/cpp/improved_siddon_precomputed.cpp
omegatomo/cpp/inveon.h
omegatomo/cpp/inveonMain.cpp
omegatomo/cpp/inveon_list2matlab.cpp
omegatomo/cpp/iterStep.h
omegatomo/cpp/libHeader.h
omegatomo/cpp/libInveon.h
omegatomo/cpp/libRoot.h
omegatomo/cpp/loadRootData.cpp
omegatomo/cpp/mexFunktio.h
omegatomo/cpp/mfunctions.h
omegatomo/cpp/multi_gpu_reconstruction.h
omegatomo/cpp/omega_maincpp.cpp
omegatomo/cpp/opencl.hpp
omegatomo/cpp/opencl_error.hpp
omegatomo/cpp/precomp.h
omegatomo/cpp/priors.h
omegatomo/cpp/projector_functions.h
omegatomo/cpp/projector_mex.cpp
omegatomo/cpp/projector_mexSingle.cpp
omegatomo/cpp/reconstructionAF.h
omegatomo/cpp/rootImport.h
omegatomo/cpp/saveSinogram.h
omegatomo/cpp/sinoLib.h
omegatomo/cpp/structs.h
omegatomo/cpp/subiterStep.h
omegatomo/fileio/__init__.py
omegatomo/fileio/loadData.py
omegatomo/fileio/loadGATESPECTData.py
omegatomo/fileio/loadInterfile.py
omegatomo/fileio/loadInveon.py
omegatomo/fileio/loadNikonData.py
omegatomo-2.1.0rc9.dist-info/licenses/LICENSE
omegatomo-2.1.0rc9.dist-info/METADATA
omegatomo-2.1.0rc9.dist-info/WHEEL
omegatomo-2.1.0rc9.dist-info/top_level.txt
omegatomo-2.1.0rc9.dist-info/RECORD
