Metadata-Version: 2.4
Name: omegatomo
Version: 2.1.0rc9
Summary: Open-source multi-dimensional tomographic reconstruction software for Python.
Author-email: Ville-Veikko Wettenhovi <villewe@uef.fi>, Niilo Saarlemo <niilo.saarlemo@uef.fi>
License-Expression: GPL-3.0-only
Project-URL: Homepage, https://github.com/villekf/OMEGA
Project-URL: Issues, https://github.com/villekf/OMEGA/issues
Project-URL: Documentation, https://omega-doc.readthedocs.io/en/latest/index.html
Project-URL: releasenotes, https://github.com/villekf/OMEGA/blob/master/release_notes.md
Keywords: tomography,tomographic,PET,CT,SPECT,image reconstruction
Classifier: Programming Language :: Python :: 3
Classifier: Operating System :: Microsoft :: Windows
Classifier: Operating System :: POSIX :: Linux
Requires-Python: >=3.6
License-File: LICENSE
Requires-Dist: numpy
Requires-Dist: pymatreader
Requires-Dist: arrayfire
Requires-Dist: scikit-image
Requires-Dist: SimpleITK
Provides-Extra: cupy
Requires-Dist: cupy; extra == "cupy"
Provides-Extra: pyopencl
Requires-Dist: pyopencl; extra == "pyopencl"
Provides-Extra: pytorch
Requires-Dist: torch; extra == "pytorch"
Requires-Dist: cupy; extra == "pytorch"
Dynamic: license-file
